{"sections":{"1655262807c96f0d82":{"type":"slideshow","disabled":true,"blocks":{"16552628075b24157d-0":{"type":"image","settings":{"image_position":"center center","mobile_image_position":"center center","slide_link":"","subheading":"Tell your story","title":"Two line\nslide heading","title_size":84,"title_size_mobile":46,"text":"<p>And optional subtext<\/p>","enlarge_text":true,"button_label_1":"Shop this","button_url_1":"","button_label_2":"Shop all","button_url_2":"","text_alignment":"center center"}},"16552628075b24157d-1":{"type":"image","settings":{"image_position":"center center","mobile_image_position":"center center","slide_link":"","subheading":"Tell your story","title":"Two line\nslide heading","title_size":84,"title_size_mobile":46,"text":"<p>And optional subtext<\/p>","enlarge_text":true,"button_label_1":"Shop this","button_url_1":"","button_label_2":"Shop all","button_url_2":"","text_alignment":"center center"}}},"block_order":["16552628075b24157d-0","16552628075b24157d-1"],"settings":{"height":"fixed","height_desktop":600,"height_mobile":460,"full_width":true,"mobile_overlay_under":false,"overlay_style":"shadow","slide_transition":"fade","slide_navigation":"arrows","autoplay":true,"autoplay_speed":7}},"main":{"type":"main-article","settings":{"show_date":false,"show_author":false,"show_article_tags":false,"show_sharing_icons":false,"show_featured_image":true,"full_width_image":false,"featured_image_height":"huge","enable_title_overlay":false,"overlay_style":"full image-overlay--bg-shadow"}},"165242975816266c3b":{"type":"custom-row","disabled":true,"blocks":{"16524297583da89d64-0":{"type":"image","settings":{"width":"half","image":"shopify:\/\/shop_images\/image-2_1.jpg","image_position":"center center","height":"adapt","height_desktop":600,"height_mobile":500,"subheading":"","title":"","text":"","enlarge_text":false,"button_label":"","image_link":"","text_alignment":"center center","mobile_overlay_under":false,"overlay_style":"shadow"}},"16524297583da89d64-1":{"type":"text","settings":{"width":"half","subheading":"","title":"Two poisonous substances combined","text":"<p>Two poisonous substances combined, chlorine and sodium, transform into salt. And salt seasons the food of humankind throughout the world. The power of unexpected combinations. When I read about this it reminded me of a giant notebook. Unexpected combinations happen in those paper pages too. Thoughts, notes from books, drawings of things in the street. They all combine together like ingredients in a large cast iron pot. <\/p>","button_label":"Back to top","button_link":"https:\/\/postalco.com","button_style":"primary","text_alignment":"left"}}},"block_order":["16524297583da89d64-0","16524297583da89d64-1"],"settings":{"alignment":"top"}}},"order":["1655262807c96f0d82","main","165242975816266c3b"]}