{"sections":{"1654742632fd500141":{"type":"collection-list","disabled":true,"blocks":{"f4709294-c45c-48f9-b0e8-8701ac972ded":{"type":"collection","settings":{"collection":"key-holder"}},"ed51e886-7d22-4df3-bc56-517c24a3e000":{"type":"collection","settings":{"collection":"jackets"}}},"block_order":["f4709294-c45c-48f9-b0e8-8701ac972ded","ed51e886-7d22-4df3-bc56-517c24a3e000"],"settings":{"title":"","enable_carousel":false,"grid":3,"use_alt_bg":false,"full_width":false}},"16534433682fa2ab53":{"type":"slideshow","disabled":true,"blocks":{"16534433681f4b636b-0":{"type":"image","settings":{"image":"shopify:\/\/shop_images\/2022-04-21_13.46.47.png","image_position":"top left","mobile_image_position":"center center","slide_link":"","subheading":"","title":"","title_size":84,"title_size_mobile":46,"text":"","enlarge_text":true,"button_label_1":"","button_url_1":"","button_label_2":"","button_url_2":"","text_alignment":"center center"}}},"block_order":["16534433681f4b636b-0"],"settings":{"height":"fixed","height_desktop":600,"height_mobile":460,"full_width":true,"mobile_overlay_under":false,"overlay_style":"shadow","slide_transition":"fade","slide_navigation":"arrows","autoplay":false,"autoplay_speed":7}},"1655350188efa73cb0":{"type":"gallery","disabled":true,"blocks":{"16553501882a8b9119-0":{"type":"image","settings":{"alignment":"center center","enlarge_image":true,"subheading":"Gallery","title":"Tell your story","button_label":"","link":"","text_alignment":"bottom left"}},"16553501882a8b9119-1":{"type":"image","settings":{"alignment":"center center","enlarge_image":false,"subheading":"Gallery","title":"Tell your story","button_label":"","link":"","text_alignment":"bottom left"}},"16553501882a8b9119-2":{"type":"image","settings":{"alignment":"center center","enlarge_image":false,"subheading":"Gallery","title":"Tell your story","button_label":"","link":"","text_alignment":"bottom left"}},"16553501882a8b9119-3":{"type":"image","settings":{"alignment":"center center","enlarge_image":true,"subheading":"Gallery","title":"Tell your story","button_label":"","link":"","text_alignment":"bottom left"}}},"block_order":["16553501882a8b9119-0","16553501882a8b9119-1","16553501882a8b9119-2","16553501882a8b9119-3"],"settings":{"grid":2,"desktop_image_height":460,"mobile_image_height":400,"title_size":30,"title_size_mobile":22,"enable_margin":true,"enable_row_spacing":true,"full_width":false,"use_alt_bg":false,"enable_carousel":true,"overlay_style":"full","button_style":"primary"}},"main":{"type":"main-collection","settings":{"show_image_behind_heading":false,"heading_image_height":"medium","overlay_style":"shadow","coll_num_per_page_int":50,"grid":4,"show_vendor":false,"show_total":false,"coll_desc_pos":"above","enable_filtering":true,"collapse_tag_sidebar_by_default":true,"collapse_filters_method":"all","show_filter_counts":true,"show_disabled_filters":true,"ajax_products":false,"enable_sticky_filter":false,"filter_two_columns":false,"coll_show_sort":false,"coll_show_feat":false,"enable_subcoll":true,"subcoll_menu":"main-menu","subcoll_style":"gallery","subcoll_gall_shape":"l-64","image_position":"center center","subcoll_gall_enable_margin":false,"subcoll_gall_full_width":true,"subcoll_gall_overlay_style":"shadow","subcoll_gall_text_alignment":"bottom left","subcoll_gall_mobile_layout":"2"}},"1654742641a18cdea7":{"type":"featured-collection","disabled":true,"settings":{"title":"Featured collection","collection":"","show_vendor":false,"enable_carousel":true,"grid":4,"rows":1,"use_alt_bg":true,"show_view_all":true,"full_width":true}}},"order":["1654742632fd500141","16534433682fa2ab53","1655350188efa73cb0","main","1654742641a18cdea7"]}